{
	"version": "2.0",
	"name": "petit-salon",
	"description": "",
	"points": 1299286,
	"projection": "",
	"hierarchy": {
		"firstChunkSize": 13354, 
		"stepSize": 4, 
		"depth": 4
	},
	"offset": [-3.0261008739471436, -2.7720329761505127, -1.2610000000000001],
	"scale": [0.001, 0.001, 0.001],
	"spacing": 0.045437499999999999,
	"boundingBox": {
		"min": [-3.0261008739471436, -2.7720329761505127, -1.2610000000000001], 
		"max": [2.7898991260528563, 3.0439670238494871, 4.5549999999999997]
	},
	"encoding": "DEFAULT",
	"attributes": [
		{
			"name": "position",
			"description": "",
			"size": 12,
			"numElements": 3,
			"elementSize": 4,
			"type": "int32",
			"min": [-3.0261008739471436, -2.7720329761505127, -1.2610000000000001],
			"max": [2.7898991260528567, 2.6759670238494873, 1.587],
			"scale": [1, 1, 1],
			"offset": [0, 0, 0]
		},{
			"name": "intensity",
			"description": "",
			"size": 2,
			"numElements": 1,
			"elementSize": 2,
			"type": "uint16",
			"min": [0],
			"max": [0],
			"scale": [1],
			"offset": [0]
		},{
			"name": "return number",
			"description": "",
			"size": 1,
			"numElements": 1,
			"elementSize": 1,
			"type": "uint8",
			"min": [0],
			"max": [0],
			"scale": [1],
			"offset": [0]
		},{
			"name": "number of returns",
			"description": "",
			"size": 1,
			"numElements": 1,
			"elementSize": 1,
			"type": "uint8",
			"min": [0],
			"max": [0],
			"scale": [1],
			"offset": [0]
		},{
			"name": "classification",
			"description": "",
			"size": 1,
			"numElements": 1,
			"elementSize": 1,
			"type": "uint8",
			"histogram": [1299286, 0, 0, 0, 0, 0, 0, 0, 0, 0, 0, 0, 0, 0, 0, 0, 0, 0, 0, 0, 0, 0, 0, 0, 0, 0, 0, 0, 0, 0, 0, 0, 0, 0, 0, 0, 0, 0, 0, 0, 0, 0, 0, 0, 0, 0, 0, 0, 0, 0, 0, 0, 0, 0, 0, 0, 0, 0, 0, 0, 0, 0, 0, 0, 0, 0, 0, 0, 0, 0, 0, 0, 0, 0, 0, 0, 0, 0, 0, 0, 0, 0, 0, 0, 0, 0, 0, 0, 0, 0, 0, 0, 0, 0, 0, 0, 0, 0, 0, 0, 0, 0, 0, 0, 0, 0, 0, 0, 0, 0, 0, 0, 0, 0, 0, 0, 0, 0, 0, 0, 0, 0, 0, 0, 0, 0, 0, 0, 0, 0, 0, 0, 0, 0, 0, 0, 0, 0, 0, 0, 0, 0, 0, 0, 0, 0, 0, 0, 0, 0, 0, 0, 0, 0, 0, 0, 0, 0, 0, 0, 0, 0, 0, 0, 0, 0, 0, 0, 0, 0, 0, 0, 0, 0, 0, 0, 0, 0, 0, 0, 0, 0, 0, 0, 0, 0, 0, 0, 0, 0, 0, 0, 0, 0, 0, 0, 0, 0, 0, 0, 0, 0, 0, 0, 0, 0, 0, 0, 0, 0, 0, 0, 0, 0, 0, 0, 0, 0, 0, 0, 0, 0, 0, 0, 0, 0, 0, 0, 0, 0, 0, 0, 0, 0, 0, 0, 0, 0, 0, 0, 0, 0, 0, 0, 0, 0, 0, 0, 0, 0, 0, 0, 0, 0, 0, 0], 
			"min": [0],
			"max": [0],
			"scale": [1],
			"offset": [0]
		},{
			"name": "scan angle rank",
			"description": "",
			"size": 1,
			"numElements": 1,
			"elementSize": 1,
			"type": "uint8",
			"min": [0],
			"max": [0],
			"scale": [1],
			"offset": [0]
		},{
			"name": "user data",
			"description": "",
			"size": 1,
			"numElements": 1,
			"elementSize": 1,
			"type": "uint8",
			"min": [0],
			"max": [0],
			"scale": [1],
			"offset": [0]
		},{
			"name": "point source id",
			"description": "",
			"size": 2,
			"numElements": 1,
			"elementSize": 2,
			"type": "uint16",
			"min": [0],
			"max": [0],
			"scale": [1],
			"offset": [0]
		},{
			"name": "rgb",
			"description": "",
			"size": 6,
			"numElements": 3,
			"elementSize": 2,
			"type": "uint16",
			"min": [0, 0, 0],
			"max": [65280, 65280, 65280],
			"scale": [1, 1, 1],
			"offset": [0, 0, 0]
		},{
			"name": "NormalX",
			"description": "",
			"size": 8,
			"numElements": 1,
			"elementSize": 8,
			"type": "double",
			"min": [-0.99999904632568359],
			"max": [0.99999904632568359],
			"scale": [1],
			"offset": [0]
		},{
			"name": "NormalY",
			"description": "",
			"size": 8,
			"numElements": 1,
			"elementSize": 8,
			"type": "double",
			"min": [-0.99999904632568359],
			"max": [0.99999904632568359],
			"scale": [1],
			"offset": [0]
		},{
			"name": "NormalZ",
			"description": "",
			"size": 8,
			"numElements": 1,
			"elementSize": 8,
			"type": "double",
			"min": [-0.99999904632568359],
			"max": [0.99999904632568359],
			"scale": [1],
			"offset": [0]
		}
	]
}
